envdir-1.0.1.dist-info/RECORD
envdir-1.0.1.dist-info/DESCRIPTION.rst
envdir-1.0.1.dist-info/METADATA
envdir-1.0.1.dist-info/top_level.txt
envdir-1.0.1.dist-info/metadata.json
envdir-1.0.1.dist-info/entry_points.txt
envdir-1.0.1.dist-info/WHEEL
envdir/test_envdir.py
envdir/env.py
envdir/__main__.py
envdir/runner.py
envdir/version.py
envdir/__init__.py
