Metadata-Version: 2.0
Name: envdir
Version: 1.0.1
Summary: A Python port of daemontools' envdir.
Home-page: https://envdir.readthedocs.io/
Author: Jannis Leidel
Author-email: jannis@leidel.info
License: MIT
Platform: UNKNOWN
Classifier: Development Status :: 4 - Beta
Classifier: Intended Audience :: Developers
Classifier: License :: OSI Approved :: MIT License
Classifier: Topic :: Software Development :: Build Tools
Classifier: Programming Language :: Python :: 2
Classifier: Programming Language :: Python :: 2.7
Classifier: Programming Language :: Python :: 3
Classifier: Programming Language :: Python :: 3.4
Classifier: Programming Language :: Python :: 3.5
Classifier: Programming Language :: Python :: 3.6
